project_manager_pro/__init__.py
project_manager_pro/_meta.py
project_manager_pro/_version.py
project_manager_pro/acmd.py
project_manager_pro/dcmd.py
project_manager_pro/entry.py
project_manager_pro/exec.py
project_manager_pro/find.py
project_manager_pro/hash_b.py
project_manager_pro/lcmd.py
project_manager_pro/list.py
project_manager_pro/move.py
project_manager_pro-2022.1.21.0.dist-info/LICENCE
project_manager_pro-2022.1.21.0.dist-info/METADATA
project_manager_pro-2022.1.21.0.dist-info/WHEEL
project_manager_pro-2022.1.21.0.dist-info/entry_points.txt
project_manager_pro-2022.1.21.0.dist-info/top_level.txt
project_manager_pro-2022.1.21.0.dist-info/RECORD
