Metadata-Version: 2.1
Name: project-manager-pro
Version: 2022.1.21.0
Summary: Manage projects
Home-page: UNKNOWN
Author: FullDungeon
Author-email: ddd.dungeon@gmail.com
License: UNKNOWN
Platform: UNKNOWN
Classifier: Programming Language :: Python :: 3.8
Classifier: License :: OSI Approved :: MIT License
Classifier: Operating System :: OS Independent
Requires-Python: >=3.8
License-File: LICENCE
Requires-Dist: colorama
